{"data": [{"devices": [{"lon": 19.90674912815427, "name": "blonia", "alt": 1.5, "lat": 50.070749606821}, {"lon": 19.9155651840895, "name": "alfa", "alt": 3.0, "lat": 50.065607816004636}, {"lon": 19.909718523873615, "name": "blonia", "alt": 1.5, "lat": 50.060667559992204}], "time": 96, "packets": [], "id": 165141384842780296}, {"devices": [{"lon": 19.90674912815427, "name": "blonia", "alt": 1.5, "lat": 50.070749606821}, {"lon": 19.9155651840895, "name": "alfa", "alt": 3.0, "lat": 50.065607816004636}, {"lon": 19.909718523873615, "name": "blonia", "alt": 1.5, "lat": 50.060667559992204}], "packets": [{"source": "blonia"}, {"snr": -17.121, "rssi": -130.002, "source": "blonia", "payload": "Ping", "hops": [], "lost": true, "tx": "blonia", "duration": 93.0, "destination": "d13", "rx": "blonia"}, {"snr": -3.737, "rssi": -116.618, "source": "blonia", "payload": "Ping", "hops": [], "lost": false, "tx": "blonia", "duration": 93.0, "destination": "d13", "rx": "alfa"}], "time": 1096, "id": 273662867188871109}, {"devices": [{"lon": 19.90674912815427, "name": "blonia", "alt": 1.5, "lat": 50.070749606821}, {"lon": 19.9155651840895, "name": "alfa", "alt": 3.0, "lat": 50.065607816004636}, {"lon": 19.909718523873615, "name": "blonia", "alt": 1.5, "lat": 50.060667559992204}], "time": 1097, "packets": [], "id": 186565607918059277}, {"devices": [{"lon": 19.90674912815427, "name": "blonia", "alt": 1.5, "lat": 50.070749606821}, {"lon": 19.9155651840895, "name": "alfa", "alt": 3.0, "lat": 50.065607816004636}, {"lon": 19.909718523873615, "name": "blonia", "alt": 1.5, "lat": 50.060667559992204}], "packets": [{"source": "alfa"}, {"snr": -7.537, "rssi": -120.418, "source": "blonia", "payload": "Ping", "hops": ["alfa"], "lost": false, "tx": "alfa", "duration": 93.0, "destination": "d13", "rx": "blonia"}, {"snr": -3.737, "rssi": -116.618, "source": "blonia", "payload": "Ping", "hops": ["alfa"], "lost": false, "tx": "alfa", "duration": 93.0, "destination": "d13", "rx": "blonia"}], "time": 1191, "id": 321735876580194097}, {"devices": [{"lon": 19.90674912815427, "name": "blonia", "alt": 1.5, "lat": 50.070749606821}, {"lon": 19.9155651840895, "name": "alfa", "alt": 3.0, "lat": 50.065607816004636}, {"lon": 19.909718523873615, "name": "blonia", "alt": 1.5, "lat": 50.060667559992204}], "time": 1192, "packets": [], "id": 182739958351873214}, {"devices": [{"lon": 19.90674912815427, "name": "blonia", "alt": 1.5, "lat": 50.070749606821}, {"lon": 19.9155651840895, "name": "alfa", "alt": 3.0, "lat": 50.065607816004636}, {"lon": 19.909718523873615, "name": "blonia", "alt": 1.5, "lat": 50.060667559992204}], "packets": [{"source": "blonia"}, {"snr": -17.121, "rssi": -130.002, "source": "blonia", "payload": "Ping", "hops": [], "lost": true, "tx": "blonia", "duration": 93.0, "destination": "d13", "rx": "blonia"}, {"snr": -3.737, "rssi": -116.618, "source": "blonia", "payload": "Ping", "hops": [], "lost": false, "tx": "blonia", "duration": 93.0, "destination": "d13", "rx": "alfa"}], "time": 2192, "id": 544994657474231975}, {"devices": [{"lon": 19.90674912815427, "name": "blonia", "alt": 1.5, "lat": 50.070749606821}, {"lon": 19.9155651840895, "name": "alfa", "alt": 3.0, "lat": 50.065607816004636}, {"lon": 19.909718523873615, "name": "blonia", "alt": 1.5, "lat": 50.060667559992204}], "time": 2193, "packets": [], "id": 250784005382749226}, {"devices": [{"lon": 19.90674912815427, "name": "blonia", "alt": 1.5, "lat": 50.070749606821}, {"lon": 19.9155651840895, "name": "alfa", "alt": 3.0, "lat": 50.065607816004636}, {"lon": 19.909718523873615, "name": "blonia", "alt": 1.5, "lat": 50.060667559992204}], "packets": [{"source": "alfa"}, {"snr": -7.537, "rssi": -120.418, "source": "blonia", "payload": "Ping", "hops": ["alfa"], "lost": false, "tx": "alfa", "duration": 93.0, "destination": "d13", "rx": "blonia"}, {"snr": -3.737, "rssi": -116.618, "source": "blonia", "payload": "Ping", "hops": ["alfa"], "lost": false, "tx": "alfa", "duration": 93.0, "destination": "d13", "rx": "blonia"}], "time": 2287, "id": 314616284498946637}, {"devices": [{"lon": 19.90674912815427, "name": "blonia", "alt": 1.5, "lat": 50.070749606821}, {"lon": 19.9155651840895, "name": "alfa", "alt": 3.0, "lat": 50.065607816004636}, {"lon": 19.909718523873615, "name": "blonia", "alt": 1.5, "lat": 50.060667559992204}], "time": 2288, "packets": [], "id": 255975340567063269}, {"devices": [{"lon": 19.90674912815427, "name": "blonia", "alt": 1.5, "lat": 50.070749606821}, {"lon": 19.9155651840895, "name": "alfa", "alt": 3.0, "lat": 50.065607816004636}, {"lon": 19.909718523873615, "name": "blonia", "alt": 1.5, "lat": 50.060667559992204}], "packets": [{"source": "blonia"}, {"snr": -17.121, "rssi": -130.002, "source": "blonia", "payload": "Ping", "hops": [], "lost": true, "tx": "blonia", "duration": 93.0, "destination": "d13", "rx": "blonia"}, {"snr": -3.737, "rssi": -116.618, "source": "blonia", "payload": "Ping", "hops": [], "lost": false, "tx": "blonia", "duration": 93.0, "destination": "d13", "rx": "alfa"}], "time": 3288, "id": 175077401135266943}, {"devices": [{"lon": 19.90674912815427, "name": "blonia", "alt": 1.5, "lat": 50.070749606821}, {"lon": 19.9155651840895, "name": "alfa", "alt": 3.0, "lat": 50.065607816004636}, {"lon": 19.909718523873615, "name": "blonia", "alt": 1.5, "lat": 50.060667559992204}], "time": 3289, "packets": [], "id": 115328578394340327}, {"devices": [{"lon": 19.90674912815427, "name": "blonia", "alt": 1.5, "lat": 50.070749606821}, {"lon": 19.9155651840895, "name": "alfa", "alt": 3.0, "lat": 50.065607816004636}, {"lon": 19.909718523873615, "name": "blonia", "alt": 1.5, "lat": 50.060667559992204}], "packets": [{"source": "alfa"}, {"snr": -7.537, "rssi": -120.418, "source": "blonia", "payload": "Ping", "hops": ["alfa"], "lost": false, "tx": "alfa", "duration": 93.0, "destination": "d13", "rx": "blonia"}, {"snr": -3.737, "rssi": -116.618, "source": "blonia", "payload": "Ping", "hops": ["alfa"], "lost": false, "tx": "alfa", "duration": 93.0, "destination": "d13", "rx": "blonia"}], "time": 3383, "id": 115598223130215238}, {"devices": [{"lon": 19.90674912815427, "name": "blonia", "alt": 1.5, "lat": 50.070749606821}, {"lon": 19.9155651840895, "name": "alfa", "alt": 3.0, "lat": 50.065607816004636}, {"lon": 19.909718523873615, "name": "blonia", "alt": 1.5, "lat": 50.060667559992204}], "time": 3384, "packets": [], "id": 228457490424863756}, {"devices": [{"lon": 19.90674912815427, "name": "blonia", "alt": 1.5, "lat": 50.070749606821}, {"lon": 19.9155651840895, "name": "alfa", "alt": 3.0, "lat": 50.065607816004636}, {"lon": 19.909718523873615, "name": "blonia", "alt": 1.5, "lat": 50.060667559992204}], "packets": [{"source": "blonia"}, {"snr": -17.121, "rssi": -130.002, "source": "blonia", "payload": "Ping", "hops": [], "lost": true, "tx": "blonia", "duration": 93.0, "destination": "d13", "rx": "blonia"}, {"snr": -3.737, "rssi": -116.618, "source": "blonia", "payload": "Ping", "hops": [], "lost": false, "tx": "blonia", "duration": 93.0, "destination": "d13", "rx": "alfa"}], "time": 4384, "id": 852930977724908964}, {"devices": [{"lon": 19.90674912815427, "name": "blonia", "alt": 1.5, "lat": 50.070749606821}, {"lon": 19.9155651840895, "name": "alfa", "alt": 3.0, "lat": 50.065607816004636}, {"lon": 19.909718523873615, "name": "blonia", "alt": 1.5, "lat": 50.060667559992204}], "time": 4385, "packets": [], "id": 252709596178586272}, {"devices": [{"lon": 19.90674912815427, "name": "blonia", "alt": 1.5, "lat": 50.070749606821}, {"lon": 19.9155651840895, "name": "alfa", "alt": 3.0, "lat": 50.065607816004636}, {"lon": 19.909718523873615, "name": "blonia", "alt": 1.5, "lat": 50.060667559992204}], "packets": [{"source": "alfa"}, {"snr": -7.537, "rssi": -120.418, "source": "blonia", "payload": "Ping", "hops": ["alfa"], "lost": false, "tx": "alfa", "duration": 93.0, "destination": "d13", "rx": "blonia"}, {"snr": -3.737, "rssi": -116.618, "source": "blonia", "payload": "Ping", "hops": ["alfa"], "lost": false, "tx": "alfa", "duration": 93.0, "destination": "d13", "rx": "blonia"}], "time": 4479, "id": 271849289731296397}, {"devices": [{"lon": 19.90674912815427, "name": "blonia", "alt": 1.5, "lat": 50.070749606821}, {"lon": 19.9155651840895, "name": "alfa", "alt": 3.0, "lat": 50.065607816004636}, {"lon": 19.909718523873615, "name": "blonia", "alt": 1.5, "lat": 50.060667559992204}], "time": 4480, "packets": [], "id": 311019649167878239}, {"devices": [{"lon": 19.90674912815427, "name": "blonia", "alt": 1.5, "lat": 50.070749606821}, {"lon": 19.9155651840895, "name": "alfa", "alt": 3.0, "lat": 50.065607816004636}, {"lon": 19.909718523873615, "name": "blonia", "alt": 1.5, "lat": 50.060667559992204}], "packets": [{"source": "blonia"}, {"snr": -17.121, "rssi": -130.002, "source": "blonia", "payload": "Ping", "hops": [], "lost": true, "tx": "blonia", "duration": 93.0, "destination": "d13", "rx": "blonia"}, {"snr": -3.737, "rssi": -116.618, "source": "blonia", "payload": "Ping", "hops": [], "lost": false, "tx": "blonia", "duration": 93.0, "destination": "d13", "rx": "alfa"}], "time": 5480, "id": 333942786944078758}, {"devices": [{"lon": 19.90674912815427, "name": "blonia", "alt": 1.5, "lat": 50.070749606821}, {"lon": 19.9155651840895, "name": "alfa", "alt": 3.0, "lat": 50.065607816004636}, {"lon": 19.909718523873615, "name": "blonia", "alt": 1.5, "lat": 50.060667559992204}], "time": 5481, "packets": [], "id": 573719418554022173}, {"devices": [{"lon": 19.90674912815427, "name": "blonia", "alt": 1.5, "lat": 50.070749606821}, {"lon": 19.9155651840895, "name": "alfa", "alt": 3.0, "lat": 50.065607816004636}, {"lon": 19.909718523873615, "name": "blonia", "alt": 1.5, "lat": 50.060667559992204}], "packets": [{"source": "alfa"}, {"snr": -7.537, "rssi": -120.418, "source": "blonia", "payload": "Ping", "hops": ["alfa"], "lost": false, "tx": "alfa", "duration": 93.0, "destination": "d13", "rx": "blonia"}, {"snr": -3.737, "rssi": -116.618, "source": "blonia", "payload": "Ping", "hops": ["alfa"], "lost": false, "tx": "alfa", "duration": 93.0, "destination": "d13", "rx": "blonia"}], "time": 5575, "id": 127696419657901289}, {"devices": [{"lon": 19.90674912815427, "name": "blonia", "alt": 1.5, "lat": 50.070749606821}, {"lon": 19.9155651840895, "name": "alfa", "alt": 3.0, "lat": 50.065607816004636}, {"lon": 19.909718523873615, "name": "blonia", "alt": 1.5, "lat": 50.060667559992204}], "time": 5576, "packets": [], "id": 118845536892433162}, {"devices": [{"lon": 19.90674912815427, "name": "blonia", "alt": 1.5, "lat": 50.070749606821}, {"lon": 19.9155651840895, "name": "alfa", "alt": 3.0, "lat": 50.065607816004636}, {"lon": 19.909718523873615, "name": "blonia", "alt": 1.5, "lat": 50.060667559992204}], "packets": [{"source": "blonia"}, {"snr": -17.121, "rssi": -130.002, "source": "blonia", "payload": "Ping", "hops": [], "lost": true, "tx": "blonia", "duration": 93.0, "destination": "d13", "rx": "blonia"}, {"snr": -3.737, "rssi": -116.618, "source": "blonia", "payload": "Ping", "hops": [], "lost": false, "tx": "blonia", "duration": 93.0, "destination": "d13", "rx": "alfa"}], "time": 6576, "id": 229772877208066795}, {"devices": [{"lon": 19.90674912815427, "name": "blonia", "alt": 1.5, "lat": 50.070749606821}, {"lon": 19.9155651840895, "name": "alfa", "alt": 3.0, "lat": 50.065607816004636}, {"lon": 19.909718523873615, "name": "blonia", "alt": 1.5, "lat": 50.060667559992204}], "time": 6577, "packets": [], "id": 826985483639269688}, {"devices": [{"lon": 19.90674912815427, "name": "blonia", "alt": 1.5, "lat": 50.070749606821}, {"lon": 19.9155651840895, "name": "alfa", "alt": 3.0, "lat": 50.065607816004636}, {"lon": 19.909718523873615, "name": "blonia", "alt": 1.5, "lat": 50.060667559992204}], "packets": [{"source": "alfa"}, {"snr": -7.537, "rssi": -120.418, "source": "blonia", "payload": "Ping", "hops": ["alfa"], "lost": false, "tx": "alfa", "duration": 93.0, "destination": "d13", "rx": "blonia"}, {"snr": -3.737, "rssi": -116.618, "source": "blonia", "payload": "Ping", "hops": ["alfa"], "lost": false, "tx": "alfa", "duration": 93.0, "destination": "d13", "rx": "blonia"}], "time": 6671, "id": 175565555384148300}, {"devices": [{"lon": 19.90674912815427, "name": "blonia", "alt": 1.5, "lat": 50.070749606821}, {"lon": 19.9155651840895, "name": "alfa", "alt": 3.0, "lat": 50.065607816004636}, {"lon": 19.909718523873615, "name": "blonia", "alt": 1.5, "lat": 50.060667559992204}], "time": 6672, "packets": [], "id": 262753517635668771}, {"devices": [{"lon": 19.90674912815427, "name": "blonia", "alt": 1.5, "lat": 50.070749606821}, {"lon": 19.9155651840895, "name": "alfa", "alt": 3.0, "lat": 50.065607816004636}, {"lon": 19.909718523873615, "name": "blonia", "alt": 1.5, "lat": 50.060667559992204}], "packets": [{"source": "blonia"}, {"snr": -17.121, "rssi": -130.002, "source": "blonia", "payload": "Ping", "hops": [], "lost": true, "tx": "blonia", "duration": 93.0, "destination": "d13", "rx": "blonia"}, {"snr": -3.737, "rssi": -116.618, "source": "blonia", "payload": "Ping", "hops": [], "lost": false, "tx": "blonia", "duration": 93.0, "destination": "d13", "rx": "alfa"}], "time": 7672, "id": 180378560925902075}, {"devices": [{"lon": 19.90674912815427, "name": "blonia", "alt": 1.5, "lat": 50.070749606821}, {"lon": 19.9155651840895, "name": "alfa", "alt": 3.0, "lat": 50.065607816004636}, {"lon": 19.909718523873615, "name": "blonia", "alt": 1.5, "lat": 50.060667559992204}], "time": 7673, "packets": [], "id": 179901500028601691}, {"devices": [{"lon": 19.90674912815427, "name": "blonia", "alt": 1.5, "lat": 50.070749606821}, {"lon": 19.9155651840895, "name": "alfa", "alt": 3.0, "lat": 50.065607816004636}, {"lon": 19.909718523873615, "name": "blonia", "alt": 1.5, "lat": 50.060667559992204}], "packets": [{"source": "alfa"}, {"snr": -7.537, "rssi": -120.418, "source": "blonia", "payload": "Ping", "hops": ["alfa"], "lost": false, "tx": "alfa", "duration": 93.0, "destination": "d13", "rx": "blonia"}, {"snr": -3.737, "rssi": -116.618, "source": "blonia", "payload": "Ping", "hops": ["alfa"], "lost": false, "tx": "alfa", "duration": 93.0, "destination": "d13", "rx": "blonia"}], "time": 7767, "id": 118078091333915133}, {"devices": [{"lon": 19.90674912815427, "name": "blonia", "alt": 1.5, "lat": 50.070749606821}, {"lon": 19.9155651840895, "name": "alfa", "alt": 3.0, "lat": 50.065607816004636}, {"lon": 19.909718523873615, "name": "blonia", "alt": 1.5, "lat": 50.060667559992204}], "time": 7768, "packets": [], "id": 227848601897429010}, {"devices": [{"lon": 19.90674912815427, "name": "blonia", "alt": 1.5, "lat": 50.070749606821}, {"lon": 19.9155651840895, "name": "alfa", "alt": 3.0, "lat": 50.065607816004636}, {"lon": 19.909718523873615, "name": "blonia", "alt": 1.5, "lat": 50.060667559992204}], "packets": [{"source": "blonia"}, {"snr": -17.121, "rssi": -130.002, "source": "blonia", "payload": "Ping", "hops": [], "lost": true, "tx": "blonia", "duration": 93.0, "destination": "d13", "rx": "blonia"}, {"snr": -3.737, "rssi": -116.618, "source": "blonia", "payload": "Ping", "hops": [], "lost": false, "tx": "blonia", "duration": 93.0, "destination": "d13", "rx": "alfa"}], "time": 8768, "id": 173932324381738367}, {"devices": [{"lon": 19.90674912815427, "name": "blonia", "alt": 1.5, "lat": 50.070749606821}, {"lon": 19.9155651840895, "name": "alfa", "alt": 3.0, "lat": 50.065607816004636}, {"lon": 19.909718523873615, "name": "blonia", "alt": 1.5, "lat": 50.060667559992204}], "time": 8769, "packets": [], "id": 214119456616564532}, {"devices": [{"lon": 19.90674912815427, "name": "blonia", "alt": 1.5, "lat": 50.070749606821}, {"lon": 19.9155651840895, "name": "alfa", "alt": 3.0, "lat": 50.065607816004636}, {"lon": 19.909718523873615, "name": "blonia", "alt": 1.5, "lat": 50.060667559992204}], "packets": [{"source": "alfa"}, {"snr": -7.537, "rssi": -120.418, "source": "blonia", "payload": "Ping", "hops": ["alfa"], "lost": false, "tx": "alfa", "duration": 93.0, "destination": "d13", "rx": "blonia"}, {"snr": -3.737, "rssi": -116.618, "source": "blonia", "payload": "Ping", "hops": ["alfa"], "lost": false, "tx": "alfa", "duration": 93.0, "destination": "d13", "rx": "blonia"}], "time": 8863, "id": 148861416564988095}, {"devices": [{"lon": 19.90674912815427, "name": "blonia", "alt": 1.5, "lat": 50.070749606821}, {"lon": 19.9155651840895, "name": "alfa", "alt": 3.0, "lat": 50.065607816004636}, {"lon": 19.909718523873615, "name": "blonia", "alt": 1.5, "lat": 50.060667559992204}], "time": 8864, "packets": [], "id": 657104292496921278}, {"devices": [{"lon": 19.90674912815427, "name": "blonia", "alt": 1.5, "lat": 50.070749606821}, {"lon": 19.9155651840895, "name": "alfa", "alt": 3.0, "lat": 50.065607816004636}, {"lon": 19.909718523873615, "name": "blonia", "alt": 1.5, "lat": 50.060667559992204}], "packets": [{"source": "blonia"}, {"snr": -17.121, "rssi": -130.002, "source": "blonia", "payload": "Ping", "hops": [], "lost": true, "tx": "blonia", "duration": 93.0, "destination": "d13", "rx": "blonia"}, {"snr": -3.737, "rssi": -116.618, "source": "blonia", "payload": "Ping", "hops": [], "lost": false, "tx": "blonia", "duration": 93.0, "destination": "d13", "rx": "alfa"}], "time": 9864, "id": 497393609436315290}, {"devices": [{"lon": 19.90674912815427, "name": "blonia", "alt": 1.5, "lat": 50.070749606821}, {"lon": 19.9155651840895, "name": "alfa", "alt": 3.0, "lat": 50.065607816004636}, {"lon": 19.909718523873615, "name": "blonia", "alt": 1.5, "lat": 50.060667559992204}], "time": 9865, "packets": [], "id": 785458189323630871}, {"devices": [{"lon": 19.90674912815427, "name": "blonia", "alt": 1.5, "lat": 50.070749606821}, {"lon": 19.9155651840895, "name": "alfa", "alt": 3.0, "lat": 50.065607816004636}, {"lon": 19.909718523873615, "name": "blonia", "alt": 1.5, "lat": 50.060667559992204}], "packets": [{"source": "alfa"}], "time": 9959, "id": 210357168548702603}, {"devices": [{"lon": 19.90674912815427, "name": "blonia", "alt": 1.5, "lat": 50.070749606821}, {"lon": 19.9155651840895, "name": "alfa", "alt": 3.0, "lat": 50.065607816004636}, {"lon": 19.909718523873615, "name": "blonia", "alt": 1.5, "lat": 50.060667559992204}], "time": 9960, "packets": [], "id": 319084567560991974}]}